.coveragerc
.gitignore
.travis.yml
LICENSE.txt
README.md
setup.py
nmigen_soc/__init__.py
nmigen_soc/memory.py
nmigen_soc.egg-info/PKG-INFO
nmigen_soc.egg-info/SOURCES.txt
nmigen_soc.egg-info/dependency_links.txt
nmigen_soc.egg-info/requires.txt
nmigen_soc.egg-info/top_level.txt
nmigen_soc/csr/__init__.py
nmigen_soc/csr/bus.py
nmigen_soc/csr/wishbone.py
nmigen_soc/test/__init__.py
nmigen_soc/test/test_csr_bus.py
nmigen_soc/test/test_csr_wishbone.py
nmigen_soc/test/test_memory.py
nmigen_soc/test/test_wishbone_bus.py
nmigen_soc/wishbone/__init__.py
nmigen_soc/wishbone/bus.py